{
	"user_id": "532876384723",
	"wellbeingscore": 30,
	"totalpossiblescore": 100,
	"strength": {
		"dimension": [{
			"dimensionid": 1,
			"name": "satisfaction with lifestyle",
			"score": 4.7
		}, {
			"dimensionid": 2,
			"name": "Pace of Life",
			"score": 4.3
		}],
		"subscale": [{
			"subscaleid": "1_1",
			"name": "Work",
			"score": 4.7
		}, {
			"subscaleid": "1_3",
			"name": "Family Life",
			"score": 4.5
		}, {
			"subscaleid": "1_4",
			"name": "Leisure and Social Life",
			"score": 4.5
		}]
	},
	"areasofdevelopment": {
		"dimension": [{
			"dimensionid": 1,
			"name": "Physical Health",
			"score": 1.0
		}, {
			"dimensionid": 2,
			"name": "Stress",
			"score": 1.1
		}],
		"subscale": [{
			"subscaleid": "2_2",
			"name": "Solution - oriented coping",
			"score": 4.7
		}, {
			"subscaleid": "2_5",
			"name": "'Anger out' coping",
			"score": 4.5
		}, {
			"subscaleid": "3_4",
			"name": "Leisure and Social Life",
			"score": 4.5
		}]

	}


}